tentamaker/__init__.py
tentamaker/config/config.toml
tentamaker/config/footer.tex
tentamaker/config/header.tex
tentamaker/config/instructions.tex
tentamaker/config/listings.tex
tentamaker/config/notation.tex
tentamaker/config/packages.tex
tentamaker/config/pool.tex
tentamaker/config/snapshot.tex
tentamaker/scripts/init_exam.py
tentamaker/scripts/make_exam.py
tentamaker-0.1.1.dist-info/LICENSE
tentamaker-0.1.1.dist-info/METADATA
tentamaker-0.1.1.dist-info/WHEEL
tentamaker-0.1.1.dist-info/entry_points.txt
tentamaker-0.1.1.dist-info/top_level.txt
tentamaker-0.1.1.dist-info/RECORD
