Metadata-Version: 2.1
Name: tentamaker
Version: 0.1.1
Summary: TentaMaker
Author-email: Anders Logg <logg@chalmers.se>
Classifier: Intended Audience :: Science/Research
Classifier: Programming Language :: Python :: 3
Classifier: License :: OSI Approved :: MIT License
Requires-Python: >=3.10
License-File: LICENSE
Requires-Dist: toml
